[
  {
    "title": "코스피 7% 폭락! 중동 형님들 싸움에 내 피 같은 돈만 녹아내린다!",
    "topic": "[중동발 오일 쇼크] 코스피 하루 만에 12% 대폭락… 삼성전자·SK하이닉...",
    "body_html": "<p>형들, 오늘(2026년 3월 4일) 진짜 살아있냐? 나 직장인 투자자 K다. 아침에 코스피 지수 보고 진짜 뒷목 잡고 쓰러질 뻔했잖아. 무슨 하루 만에 7%가 빠져? 이게 주식 시장이냐, 내 심장 마비 유도장이냐! 뉴스 보니까 중동 형님들 또 불꽃놀이 시작해서 기름값 폭등했다는데, 왜 그 불꽃놀이 비용을 내 계좌가 내고 있냐고!</p>\n<img src=\"https://images.unsplash.com/photo-1694194094284-83cde88cbc61?crop=entropy&cs=tinysrgb&fit=max&fm=jpg&ixid=M3w4ODQ4MjF8MHwxfHNlYXJjaHwzfHxPaWwlMjBTaG9ja3xlbnwwfDB8fHwxNzcyNjU5NTkyfDA&ixlib=rb-4.1.0&q=80&w=1080\" alt=\"[중동발 오일 쇼크] 코스피 하루 만에 12% 대폭락… 삼성전자·SK하이닉...\" style=\"width:100%; border-radius:8px; margin:16px 0 4px;\" /><p style=\"font-size:12px; color:#999; text-align:center; margin:0 0 16px;\">Photo by Jacob Padilla on Unsplash</p>\n\n\n<h3>오늘의 '호러' 대시보드</h3>\n<table style=\"width:100%; border-collapse:collapse; margin:16px 0;\">\n<tr style=\"background:#f5f5f5;\"><th style=\"padding:8px; border:1px solid #ddd;\">지표</th><th style=\"padding:8px; border:1px solid #ddd;\">현재가</th><th style=\"padding:8px; border:1px solid #ddd;\">전일 대비</th><th style=\"padding:8px; border:1px solid #ddd;\">K의 짠내 분석</th></tr>\n<tr><td style=\"padding:8px; border:1px solid #ddd;\">KOSPI</td><td style=\"padding:8px; border:1px solid #ddd;\">5,791.91</td><td style=\"padding:8px; border:1px solid #ddd;\">▼ 7.24%</td><td style=\"padding:8px; border:1px solid #ddd;\">내 계좌는 이미 마리아나 해구 바닥 뚫고 지옥 가는 중</td></tr>\n<tr><td style=\"padding:8px; border:1px solid #ddd;\">원/달러 환율</td><td style=\"padding:8px; border:1px solid #ddd;\">1,452.27원</td><td style=\"padding:8px; border:1px solid #ddd;\">▲ 0.96%</td><td style=\"padding:8px; border:1px solid #ddd;\">환율은 고속도로, 내 지갑은 일방통행 막다른 골목</td></tr>\n<tr><td style=\"padding:8px; border:1px solid #ddd;\">WTI 유가</td><td style=\"padding:8px; border:1px solid #ddd;\">$74.56</td><td style=\"padding:8px; border:1px solid #ddd;\">▲ 4.67%</td><td style=\"padding:8px; border:1px solid #ddd;\">기름값 오르면 내 따릉이 바퀴만 더 열심히 굴려야지</td></tr>\n<tr><td style=\"padding:8px; border:1px solid #ddd;\">비트코인(BTC)</td><td style=\"padding:8px; border:1px solid #ddd;\">$68,293.65</td><td style=\"padding:8px; border:1px solid #ddd;\">▼ 0.70%</td><td style=\"padding:8px; border:1px solid #ddd;\">디지털 금이라더니... 내 멘탈은 디지털 가루가 됨</td></tr>\n</table>\n\n<h3>중동발 오일 쇼크: 형님들 싸움에 내 난방비만 폭탄 맞는다</h3>\n<p>형들, 이번 중동 사태, 진짜 심상치 않아. 뉴스 보니까 한국은 석유 70%, LNG 16%를 중동에서 수입한대. 이게 무슨 말이냐면, 중동 형님들이 기침 한 번 하면 우리 경제는 폐렴 걸린다는 소리야. 기름값(WTI 유가 4.67% 상승)이 이렇게 뛰면, 당장 내 자동차 주유비는 물론이고, 겨울 난방비까지 폭탄 맞을 게 뻔하잖아. 안 그래도 영끌해서 산 아파트 이자 내느라 광합성 중인데, 이제 겨울에 집에서 덜덜 떨면서 살아야 할 판이다.</p>\n<p>이게 단순히 유가 문제로 끝나면 다행인데, 유가 오르면 물가 오르고, 물가 오르면 한국은행 형님들이 금리 인하를 못 해. 그럼 내 대출 이자는? 응, 계속 고공행진이야. 삼성전자, SK하이닉스 같은 대형주들이 코스피 7.24% 폭락에 같이 손잡고 나락 가는 거 보니까 진짜 눈앞이 캄캄하더라. 내 계좌로 치면 한 달 용돈이 증발한 셈이다. 이 정도면 중동 형님들이 내 통장 비밀번호 아는 거 아니냐?</p>\n\n\n<h3>환율은 고속도로, 비트코인은 롤러코스터... 어딜 가도 지옥이다</h3>\n<p>환율(원/달러 환율 1,452.27원)은 또 왜 이렇게 미쳐 날뛰는 건데? 달러가 이렇게 비싸지면 해외 직구는 이제 꿈도 못 꿔. 아이허브에서 영양제 사는 것도 사치고, 그냥 다이소에서 비타민C나 사 먹어야 할 판이야. 게다가 비트코인마저 빌빌 기는 거 보면 진짜 답이 없다. '디지털 금'이라더니, 전쟁 터지면 진짜 금(GOLD)으로 도망가지 왜 비트코인(BTC 0.70% 하락)을 던지냐고! 나 진짜 코인으로 한 방 노리다가 반토막 났는데, 이제는 이게 더 떨어질까 봐 밤에 잠도 못 자. 내 심장이랑 비트코인이랑 누가 먼저 터질지 내기하는 중이다.</p>\n<p>작년에도 환율 때문에 해외 투자했다가 손해 봤는데, 또 이러네. 학습 능력이 없는 건지, 아니면 그냥 내 팔자가 이런 건지 모르겠다. 진짜 전 세계에 있는 모든 악재는 왜 내 지갑이랑만 친한 건지 원. 이젠 뉴스 보기도 무섭다. 차라리 눈 감고 귀 막고 사는 게 더 행복할 것 같아.</p>\n\n\n<p><b>오늘의 결론: 나보다 더 처참하게 망가진 놈 있으면 나와봐</b></p>\n<p>중동 형님들 싸움에, 환율 폭등에, 주식 폭락에, 코인마저 빌빌 기는 이 지옥 같은 시장...<br>\n주식: 외인 형님들 도망가서 박살.<br>\n환율: 직구 포기, 기름값 상승으로 지갑 박살.<br>\n부동산: 금리 인하 물 건너가서 이자 부담 폭발.<br>\n코인: 디지털 금이라더니 그냥 디지털 숯덩이 됨.<br>\n나처럼 전방위로 물려서 고통받는 형들 있으면 댓글 달아봐라. 서로 계좌 까고 누가 더 짠내 나는지 대결이나 해보자. 나보다 심하면 내가 마음으로 쥬시쿨 한 잔 쏜다. ㅠㅠ</p>\n\n<img src=\"https://images.unsplash.com/photo-1419242902214-272b3f66ee7a?crop=entropy&cs=tinysrgb&fit=max&fm=jpg&ixid=M3w4ODQ4MjF8MHwxfHNlYXJjaHwzfHxTdGFycnklMjBOaWdodHxlbnwwfDB8fHwxNzcyNjU5NTkzfDA&ixlib=rb-4.1.0&q=80&w=1080\" alt=\"[중동발 오일 쇼크] 코스피 하루 만에 12% 대폭락… 삼성전자·SK하이닉...\" style=\"width:100%; border-radius:8px; margin:24px 0 4px;\" /><p style=\"font-size:12px; color:#999; text-align:center; margin:0 0 8px;\">Photo by Vincentiu Solomon on Unsplash</p>",
    "tags": [
      "코스피",
      "오일쇼크",
      "중동사태",
      "K-투자자",
      "비트코인"
    ],
    "estimated_reading_time": "4분",
    "market_summary_lines": [
      "KOSPI: 5,791.91 (-7.24%)",
      "KOSDAQ: 1,137.70 (-4.62%)",
      "USD_KRW: 1,452.27 (+0.96%)",
      "EUR_KRW: 1,698.17 (+0.09%)",
      "JPY_KRW: 9.23 (+0.61%)",
      "WTI_OIL: 74.56 (+4.67%)",
      "GOLD: 5,107.40 (-3.53%)",
      "BTC_USD: 68,293.65 (-0.70%)"
    ],
    "image_ids": [
      "photo-1694194094284-83cde88cbc61",
      "photo-1419242902214-272b3f66ee7a"
    ],
    "gif_ids": []
  },
  {
    "title": "환율 1,452원? 야, 2026년에 내 지갑은 이미 시한부 선고받았다!",
    "topic": "원달러 환율 1,452원 시대 분석",
    "body_html": "<p>형들, 오늘(2026년 3월 4일) 진짜 쌍욕 안 나오면 보살 아니냐? 나 직장인 투자자 K다. 아침에 눈 뜨자마자 핸드폰으로 계좌 확인하는데, 코스피가 무슨 번지점프를 하고 있질 않나, 환율은 또 미친 듯이 치솟아서 1,452원을 넘어가 버렸더라. 진짜 액정 냅다 던질 뻔했잖아. 내 지갑은 이미 시한부 선고받았어. 병명은 '글로벌 경제 위기 합병증'이다.</p>\n<img src=\"https://images.unsplash.com/photo-1635840420855-bb9d38c9b37b?crop=entropy&cs=tinysrgb&fit=max&fm=jpg&ixid=M3w4ODQ4MjF8MHwxfHNlYXJjaHwxfHxXb24lMjBEb2xsYXIlMjBFeGNoYW5nZSUyMFJhdGUlMjAxNDUyJTIwS1JXJTIwRXJhJTIwQW5hbHlzaXN8ZW58MHwwfHx8MTc3MjY1OTU5NHww&ixlib=rb-4.1.0&q=80&w=1080\" alt=\"원달러 환율 1,452원 시대 분석\" style=\"width:100%; border-radius:8px; margin:16px 0 4px;\" /><p style=\"font-size:12px; color:#999; text-align:center; margin:0 0 16px;\">Photo by rc.xyz NFT gallery on Unsplash</p>\n\n\n<h3>오늘의 '호러' 대시보드</h3>\n<table style=\"width:100%; border-collapse:collapse; margin:16px 0;\">\n<tr style=\"background:#f5f5f5;\"><th style=\"padding:8px; border:1px solid #ddd;\">지표</th><th style=\"padding:8px; border:1px solid #ddd;\">현재가</th><th style=\"padding:8px; border:1px solid #ddd;\">전일 대비</th><th style=\"padding:8px; border:1px solid #ddd;\">K의 짠내 분석</th></tr>\n<tr><td style=\"padding:8px; border:1px solid #ddd;\">KOSPI</td><td style=\"padding:8px; border:1px solid #ddd;\">5,791.91</td><td style=\"padding:8px; border:1px solid #ddd;\">▼ 7.24%</td><td style=\"padding:8px; border:1px solid #ddd;\">코스피는 번지점프, 내 종목은 지하 뚫는 중</td></tr>\n<tr><td style=\"padding:8px; border:1px solid #ddd;\">원/달러 환율</td><td style=\"padding:8px; border:1px solid #ddd;\">1,452.27원</td><td style=\"padding:8px; border:1px solid #ddd;\">▲ 0.96%</td><td style=\"padding:8px; border:1px solid #ddd;\">환율이 고속도로 속도위반 수준... 직구는 이제 꿈이다</td></tr>\n<tr><td style=\"padding:8px; border:1px solid #ddd;\">WTI 유가</td><td style=\"padding:8px; border:1px solid #ddd;\">$74.56</td><td style=\"padding:8px; border:1px solid #ddd;\">▲ 4.67%</td><td style=\"padding:8px; border:1px solid #ddd;\">기름값 오르면 내 따릉이 바퀴만 더 열심히 굴려야지</td></tr>\n<tr><td style=\"padding:8px; border:1px solid #ddd;\">비트코인(BTC)</td><td style=\"padding:8px; border:1px solid #ddd;\">$68,293.65</td><td style=\"padding:8px; border:1px solid #ddd;\">▼ 0.70%</td><td style=\"padding:8px; border:1px solid #ddd;\">디지털 금이라더니, 왜 금값 떨어질 때 같이 눈치 보냐?</td></tr>\n</table>\n\n<h3>환율은 롤러코스터, 내 지갑은 텅 빈 놀이기구</h3>\n<p>형들, 환율 1,452원 이거 실화냐? 원/달러 환율이 0.96%나 치솟아서 1,452.27원 찍었고, 유로화(EUR_KRW 1,698.17원)랑 엔화(JPY_KRW 9.23원)도 덩달아 다 오르는 중이야. 이건 무슨 글로벌 '달러 줍줍' 대작전이냐? 분석해보면 결국 달러 강세는 안전자산 선호 심리 폭발 + Fed 형님들의 긴축 기조 유지 시그널 때문일 거야. 코스피가 7% 넘게 빠진 거 보면 외국인 형들이 한국에서 돈 빼서 달러로 튀는 게 뻔하잖아. 그럼 물가는 또 오르고, 한국은행 형님들은 금리 인하? 꿈 깨야지. 내 대출 이자만 또 폭발하게 생겼다.</p>\n<p>이 환율이면 이제 아이허브 영양제 직구는 사치다. 해외여행은 꿈도 못 꾸고, 수입 물가 오르니 마트 가는 것도 무섭다. 내 월급 빼고 다 오르는 이 매직! 진짜 뒷목 잡고 쓰러질 뻔했다. 이쯤 되면 환율이 아니라 내 지갑이 고속도로에서 속도위반 딱지 떼이고 있는 기분이다.</p>\n\n\n<h3>코스피는 마리아나 해구, 유가는 에베레스트 등반 중</h3>\n<p>와, 진짜 오늘 장 보면서 손가락이 덜덜 떨리더라. 코스피는 5,791.91을 찍으면서 7.24% 박살 났고, 코스닥도 1,137.70으로 4.62%나 빠졌어. 내 계좌는 이미 나노 단위로 분해된 지 오래다. 근데 더 킹 받는 건 유가야. WTI 유가가 $74.56로 4.67%나 올랐네? 주식 시장이 이렇게 개박살 나는 와중에 유가가 오르는 건 무슨 경우냐. 이건 그냥 헬게이트 오픈 아니냐.</p>\n<p>주식 시장 박살은 글로벌 경기 침체 우려 + 국내 기업 실적 악화 전망 + 외국인 매도 폭탄의 콤보일 거야. 여기에 유가가 오르면? 기업들은 생산비용 올라가고, 소비자는 물가 부담 가중돼서 지갑 닫고, 그럼 기업 실적은 더 나빠지는 악순환이 시작되는 거지. 유가가 오르는 건 중동 불안이나 공급 축소 우려 때문일 텐데, 형들은 이 와중에 기름값 올릴 생각만 하냐? 내 주식은 이미 마이너스 50%가 기본 장착인데, 오늘은 추가 폭탄 맞아서 '계좌 사망' 선고 받았다. 기름값 오르니 출퇴근 유류비도 부담이고, 배달 시켜 먹으려 해도 배달비가 무섭다. 동공 지진 멈추질 않네.</p>\n\n\n<p><b>오늘의 결론: 나보다 더 처참하게 망가진 놈 있으면 나와봐</b></p>\n<p>형들, 나만 이런 거 아니지? 비트코인(BTC $68,293.65)도 겨우 버티는 줄 알았는데, 0.70% 찔끔 빠졌네. '디지털 금'이라더니, 왜 진짜 금(GOLD $5,107.40, -3.53%)이랑 손잡고 같이 떨어지냐? 진짜 금도 오늘 배신 때렸어. 부동산? 고금리 때문에 이자 내느라 광합성 중이야. 어딜 가도 지옥이다. 진짜 나처럼 전방위로 물려서 고통받는 형들 있으면 댓글 달아봐라. 서로 계좌 까고 누가 더 짠내 나는지 대결이나 해보자. 나보다 심하면 내가 마음으로 쥬시쿨 한 잔 쏜다. ㅠㅠ</p>\n\n<img src=\"https://images.unsplash.com/photo-1669939959116-9f9b3333575e?crop=entropy&cs=tinysrgb&fit=max&fm=jpg&ixid=M3w4ODQ4MjF8MHwxfHNlYXJjaHwyfHxNaXN0eSUyMG1vdW50YWluc2NhcGV8ZW58MHwwfHx8MTc3MjY1OTU5NHww&ixlib=rb-4.1.0&q=80&w=1080\" alt=\"원달러 환율 1,452원 시대 분석\" style=\"width:100%; border-radius:8px; margin:24px 0 4px;\" /><p style=\"font-size:12px; color:#999; text-align:center; margin:0 0 8px;\">Photo by Drew Tilk on Unsplash</p>",
    "tags": [
      "환율",
      "코스피",
      "직구",
      "유가",
      "개미투자자"
    ],
    "estimated_reading_time": "4분",
    "market_summary_lines": [
      "KOSPI: 5,791.91 (-7.24%)",
      "KOSDAQ: 1,137.70 (-4.62%)",
      "USD_KRW: 1,452.27 (+0.96%)",
      "EUR_KRW: 1,698.17 (+0.09%)",
      "JPY_KRW: 9.23 (+0.61%)",
      "WTI_OIL: 74.56 (+4.67%)",
      "GOLD: 5,107.40 (-3.53%)",
      "BTC_USD: 68,293.65 (-0.70%)"
    ],
    "image_ids": [
      "photo-1635840420855-bb9d38c9b37b",
      "photo-1669939959116-9f9b3333575e"
    ],
    "gif_ids": []
  },
  {
    "title": "비트코인 68K는 축제? 내 계좌는 지하실 뚫고 지하 핵까지 갔다!",
    "topic": "비트코인 $68,294 시대 투자 전략",
    "body_html": "<p>형들, 오늘(2026년 03월 04일) 아침부터 내 뒷목이 뻐근하다 못해 끊어지는 줄 알았다. 비트코인 형님이 68,000달러 넘었다는 소식에 \"드디어 내 코인도 좀 오르려나!\" 싶었는데, 내 계좌는 왜 또 파란불이냐? 그것도 모자라 코스피, 코스닥은 무슨 전쟁 난 줄 알았네. 이거 나만 지옥이야? 동공 지진 와서 뉴스 다시 봤잖아.</p>\n<img src=\"https://images.unsplash.com/photo-1633534415766-165181ffdbb7?crop=entropy&cs=tinysrgb&fit=max&fm=jpg&ixid=M3w4ODQ4MjF8MHwxfHNlYXJjaHwxfHxDcnlwdG9jdXJyZW5jeSUyMHRyYWRpbmd8ZW58MHwwfHx8MTc3MjY1OTU5Nnww&ixlib=rb-4.1.0&q=80&w=1080\" alt=\"비트코인 $68,294 시대 투자 전략\" style=\"width:100%; border-radius:8px; margin:16px 0 4px;\" /><p style=\"font-size:12px; color:#999; text-align:center; margin:0 0 16px;\">Photo by Tejaswin Gundala on Unsplash</p>\n\n\n<h3>오늘의 '호러' 대시보드</h3>\n<table style=\"width:100%; border-collapse:collapse; margin:16px 0;\">\n<tr style=\"background:#f5f5f5;\"><th style=\"padding:8px; border:1px solid #ddd;\">지표</th><th style=\"padding:8px; border:1px solid #ddd;\">현재가</th><th style=\"padding:8px; border:1px solid #ddd;\">전일 대비</th><th style=\"padding:8px; border:1px solid #ddd;\">K의 짠내 분석</th></tr>\n<tr><td style=\"padding:8px; border:1px solid #ddd;\">KOSPI</td><td style=\"padding:8px; border:1px solid #ddd;\">5,791.91</td><td style=\"padding:8px; border:1px solid #ddd;\">▼ 7.24%</td><td style=\"padding:8px; border:1px solid #ddd;\">내 계좌, 코스피 따라 지하실 뚫고 지하 핵까지 가는 중</td></tr>\n<tr><td style=\"padding:8px; border:1px solid #ddd;\">KOSDAQ</td><td style=\"padding:8px; border:1px solid #ddd;\">1,137.70</td><td style=\"padding:8px; border:1px solid #ddd;\">▼ 4.62%</td><td style=\"padding:8px; border:1px solid #ddd;\">코스닥은 롤러코스터, 내 심장은 번지점프</td></tr>\n<tr><td style=\"padding:8px; border:1px solid #ddd;\">원/달러 환율</td><td style=\"padding:8px; border:1px solid #ddd;\">1,452.27원</td><td style=\"padding:8px; border:1px solid #ddd;\">▲ 0.96%</td><td style=\"padding:8px; border:1px solid #ddd;\">환율이 고속도로 속도위반, 내 지갑은 멈춤</td></tr>\n<tr><td style=\"padding:8px; border:1px solid #ddd;\">WTI 유가</td><td style=\"padding:8px; border:1px solid #ddd;\">$74.56</td><td style=\"padding:8px; border:1px solid #ddd;\">▲ 4.67%</td><td style=\"padding:8px; border:1px solid #ddd;\">기름값 오르면 내 따릉이 바퀴만 더 열심히 굴려야지</td></tr>\n<tr><td style=\"padding:8px; border:1px solid #ddd;\">비트코인(BTC)</td><td style=\"padding:8px; border:1px solid #ddd;\">$68,293.65</td><td style=\"padding:8px; border:1px solid #ddd;\">▼ 0.70%</td><td style=\"padding:8px; border:1px solid #ddd;\">디지털 금이라더니, 내 계좌는 디지털 숯덩이...</td></tr>\n</table>\n\n<h3>비트코인 68K는 축제, 내 계좌는 장례식</h3>\n<p>야, 형들. 비트코인이 68,293.65달러 찍었다는데, 왜 내 건 -0.70%냐? 이 정도면 그냥 횡보 아니냐고? 내가 샀을 땐 7만불 넘는다고 온갖 유튜버들이 난리 쳤었는데, 왜 내 손만 거치면 이렇게 힘을 못 쓰냐? '디지털 금'이라며! 주식 시장 박살 나면 안전 자산이라며! 근데 왜 내 계좌만 박살 나냐고. 이거 완전 나한테만 가짜 금 파는 거 아니냐? 예전에 김치 프리미엄 붙어서 샀다가 반토막 났을 때도 이랬거든. 그때도 정신 승리한다고 \"나중에 오르겠지\" 했는데, 3년째 존버 중이다. 내 비트코인 잔고 보면 솔직히 배민 VIP 탈출하고 일반 회원으로 강등될 판이다.</p>\n<p>비트코인 형님들이 아무리 우주 뚫고 간다 해도, 결국 시장 전체가 공포에 질리면 기관 형님들은 일단 팔고 보더라고. 우리 같은 개미들만 \"이번엔 다를 거야!\" 외치다가 통수 맞는 거지. 내 코인들이 나한테만 왜 이러는지 모르겠네. 진짜 눈물 난다.</p>\n\n\n<h3>코스피는 번지점프, 내 종목은 자유낙하</h3>\n<p>오늘 코스피는 5,791.91로 -7.24% 빠지고, 코스닥은 1,137.70으로 -4.62% 박살 났잖아. 이건 무슨 폭락장 수준이 아니라 대환장 파티 아니냐? 외인 형님들이랑 기관 형님들 매도 버튼 누르느라 손가락 부러지는 줄 알았을 거야. 시장에 무슨 공포탄이라도 터졌나? 아니면 미국 형님들이 금리 인하 안 한다고 또 엄포 놓은 건가? 환율까지 1,452.27원 찍는 거 보니까, 개미들 등골 빼먹으려고 작정한 거지.</p>\n<p>내 주식 계좌 보니까 지난주에 산 떡상 기대 종목이 오늘 아침에 떡락해서 치킨 3마리 값이 증발했다. 진짜 액정 깰 뻔했어. 연쇄 반응 따져보면, 글로벌 경기 침체 우려가 커지면 기업 실적 안 좋아지고, 그럼 주가 빠지고, 그럼 투자 심리 위축되고... 결국 내 지갑이 나노 단위로 분해되는 거지. 이게 무슨 투자냐, 그냥 내 돈 헌납하는 거지. 진짜 화딱지 난다.</p>\n\n\n<h3>환율은 고속도로, 기름값은 KTX, 내 지갑은 멈춤</h3>\n<p>달러 환율이 1,452.27원까지 치솟았지? 이거 이러다 1,500원 찍는 거 아니냐? 환율 오르면 수입 물가 다 오르고, 기름값도 WTI 유가가 74.56달러까지 튀니까 내 차에 기름 넣으러 갈 때마다 심장이 벌렁거린다. 아니, 내가 무슨 죄를 지었다고 기름값에 환율까지 나를 괴롭히냐고! 이러면 해외 직구는 꿈도 못 꾸고, 회사 점심값도 오르고, 심지어 택시비도 오르겠네.</p>\n<p>내 월급은 그대로인데 지출만 늘어나는 마법. 이게 바로 'K-인플레이션' 아니냐? 이러다 진짜 회사까지 걸어 다니면서 광합성 해야 할 판이다. 유가 오르면 물류비 오르고, 그럼 또 물가 오르고, 그럼 또 한은 형님들이 금리 못 내리고... 내 대출 이자는 또 언제 내려가냐고! 이젠 고통의 도미노 게임에 내가 말려들고 있는 기분이다.</p>\n\n\n<p><b>오늘의 결론: 나보다 더 처참하게 망가진 놈 있으면 나와봐</b></p>\n<p>형들, 솔직히 말해봐. 나만 이런 거 아니지? 주식은 박살 났고, 코인은 존버 중인데 마이너스고, 부동산은 영끌해서 이자 내느라 허리 휘고, 채권은 작년에 통수 맞았고... 어딜 가도 지옥이다. 진짜 나보다 더 심한 놈 있으면 댓글 달아봐라. 내가 진심으로 어깨 토닥여 줄게. 오늘 밤엔 소주 한잔 하면서 잊어야겠다. 젠장!</p>\n<img src=\"https://images.unsplash.com/photo-1719932813391-59e4e23c048d?crop=entropy&cs=tinysrgb&fit=max&fm=jpg&ixid=M3w4ODQ4MjF8MHwxfHNlYXJjaHw0fHxNaXN0eSUyME1vdW50YWluc2NhcGV8ZW58MHwwfHx8MTc3MjY1OTU5Nnww&ixlib=rb-4.1.0&q=80&w=1080\" alt=\"비트코인 $68,294 시대 투자 전략\" style=\"width:100%; border-radius:8px; margin:24px 0 4px;\" /><p style=\"font-size:12px; color:#999; text-align:center; margin:0 0 8px;\">Photo by Jamie Cooper on Unsplash</p>",
    "tags": [
      "비트코인",
      "코스피",
      "주식",
      "환율",
      "K-투자자"
    ],
    "estimated_reading_time": "3분",
    "market_summary_lines": [
      "KOSPI: 5,791.91 (-7.24%)",
      "KOSDAQ: 1,137.70 (-4.62%)",
      "USD_KRW: 1,452.27 (+0.96%)",
      "EUR_KRW: 1,698.17 (+0.09%)",
      "JPY_KRW: 9.23 (+0.61%)",
      "WTI_OIL: 74.56 (+4.67%)",
      "GOLD: 5,107.40 (-3.53%)",
      "BTC_USD: 68,293.65 (-0.70%)"
    ],
    "image_ids": [
      "photo-1633534415766-165181ffdbb7",
      "photo-1719932813391-59e4e23c048d"
    ],
    "gif_ids": []
  }
]